geninstaller/__init__.py
geninstaller/cmd.py
geninstaller/config.py
geninstaller/core.py
geninstaller/database.py
geninstaller/exceptions.py
geninstaller/helpers.py
geninstaller/ploppers.py
geninstaller/migrations/__init__.py
geninstaller/migrations/migrations_2_1.py
geninstaller/plop/__init__.py
geninstaller/plop/gui/__init__.py
geninstaller/plop/gui/geninstaller.png
geninstaller/plop/gui/geninstaller_gui.py
geninstaller/plop/gui/gui_installer.py
geninstaller/plop/gui/jsondb.py
geninstaller/plop/installer/__init__.py
geninstaller/plop/installer/installer
geninstaller/silly_engine/__init__.py
geninstaller/silly_engine/ascii_map_01.py
geninstaller/silly_engine/jsondb.py
geninstaller/silly_engine/logger.py
geninstaller/silly_engine/minuit.py
geninstaller/silly_engine/router.py
geninstaller/silly_engine/text_tools.py
geninstaller-2.2.2.dist-info/licenses/LICENSE.md
geninstaller-2.2.2.dist-info/METADATA
geninstaller-2.2.2.dist-info/WHEEL
geninstaller-2.2.2.dist-info/entry_points.txt
geninstaller-2.2.2.dist-info/top_level.txt
geninstaller-2.2.2.dist-info/RECORD
