Metadata-Version: 2.4
Name: geninstaller
Version: 2.2.2
Summary: Linux universal app installer and manager, in the user's space only
Author-email: Vincent Fabre <peigne.plume@gmail.com>
Project-URL: Homepage, https://github.com/byoso/geninstaller
Project-URL: Repository, https://github.com/byoso/geninstaller
Keywords: install,installer,geninstaller,linux
Classifier: Programming Language :: Python :: 3
Classifier: Development Status :: 5 - Production/Stable
Classifier: Natural Language :: English
Requires-Python: >=3.10
License-File: LICENSE.md
Dynamic: license-file
